wtpy/CodeHelper.py
wtpy/ContractMgr.py
wtpy/CtaContext.py
wtpy/ExtModuleDefs.py
wtpy/ExtToolDefs.py
wtpy/HftContext.py
wtpy/ProductMgr.py
wtpy/SelContext.py
wtpy/SessionMgr.py
wtpy/StrategyDefs.py
wtpy/WtBtEngine.py
wtpy/WtCoreDefs.py
wtpy/WtDataDefs.py
wtpy/WtDtEngine.py
wtpy/WtDtServo.py
wtpy/WtEngine.py
wtpy/WtMsgQue.py
wtpy/WtUtilDefs.py
wtpy/__init__.py
wtpy/apps/WtBtAnalyst.py
wtpy/apps/WtCCLoader.py
wtpy/apps/WtCtaGAOptimizer.py
wtpy/apps/WtCtaOptimizer.py
wtpy/apps/WtHftOptimizer.py
wtpy/apps/WtHotPicker.py
wtpy/apps/__init__.py
wtpy/apps/datahelper/DHBaostock.py
wtpy/apps/datahelper/DHDefs.py
wtpy/apps/datahelper/DHFactory.py
wtpy/apps/datahelper/DHRqData.py
wtpy/apps/datahelper/DHTqSdk.py
wtpy/apps/datahelper/DHTushare.py
wtpy/apps/datahelper/__init__.py
wtpy/apps/datahelper/db/MysqlHelper.py
wtpy/apps/datahelper/db/__init__.py
wtpy/apps/datahelper/db/initdb_mysql.sql
wtpy/monitor/DataMgr.py
wtpy/monitor/EventReceiver.py
wtpy/monitor/PushSvr.py
wtpy/monitor/WatchDog.py
wtpy/monitor/WtBtMon.py
wtpy/monitor/WtBtSnooper.py
wtpy/monitor/WtLogger.py
wtpy/monitor/WtMonSvr.py
wtpy/monitor/__init__.py
wtpy/monitor/static/__init__.py
wtpy/monitor/static/favicon.ico
wtpy/monitor/static/console/__init__.py
wtpy/monitor/static/console/backtest.html
wtpy/monitor/static/console/index.html
wtpy/monitor/static/console/static/__init__.py
wtpy/monitor/static/console/static/css/__init__.py
wtpy/monitor/static/console/static/css/app.1e35bbc7fa3d20b13f7ab241eec33b3b.css
wtpy/monitor/static/console/static/css/backtest.e72524d8b63a5d8c8e8dc60d753be975.css
wtpy/monitor/static/console/static/css/style_black.css
wtpy/monitor/static/console/static/css/style_white.css
wtpy/monitor/static/console/static/css/static/__init__.py
wtpy/monitor/static/console/static/css/static/fonts/__init__.py
wtpy/monitor/static/console/static/css/static/fonts/element-icons.535877f.woff
wtpy/monitor/static/console/static/css/static/fonts/element-icons.732389d.ttf
wtpy-0.9.9.3.dist-info/LICENSE
wtpy-0.9.9.3.dist-info/METADATA
wtpy-0.9.9.3.dist-info/WHEEL
wtpy-0.9.9.3.dist-info/top_level.txt
wtpy-0.9.9.3.dist-info/RECORD
