Metadata-Version: 2.1
Name: wtpy
Version: 0.9.9.3
Summary: Python Sub Framework Of WonderTrader
Home-page: https://github.com/wondertrader/wtpy
Author: Wesley Liu
Author-email: silencesword@foxmail.com
License: MIT
Platform: UNKNOWN
Classifier: License :: OSI Approved :: MIT License
Classifier: Programming Language :: Python
Classifier: Programming Language :: Python :: 3
Classifier: Programming Language :: Python :: Implementation :: CPython
Classifier: Programming Language :: Python :: Implementation :: PyPy
Requires-Python: >=3.8.0
Requires-Dist: numpy
Requires-Dist: pandas (==1.3.5)
Requires-Dist: chardet
Requires-Dist: pyyaml
Requires-Dist: xlsxwriter
Requires-Dist: pyquery
Requires-Dist: psutil
Requires-Dist: fastapi
Requires-Dist: uvicorn
Requires-Dist: deap
Requires-Dist: websockets (>=10.4)
